{"orderId":"1221956401954293096","orderReference":"ELEGlcMK","status":"COMPLETED","completedDate":"2020-08-13T00:49:44.932-07:00","summary":[{"searchId":"1221966722911700329","search":"SSN Address Trace","status":"complete","result":null,"flagged":"true"},{"searchId":"1221966722987197803","search":"National Criminal Database","status":"complete","result":null,"flagged":"true"},{"searchId":"1221966723045918061","search":"National DOJ Sex Offender","status":"complete","result":null,"flagged":"true"}],"report_url":"https://assurehire.com/backgroundchecks/1221956401954293096/report"}